package/__init__.py
package/config_args.py
package/config_func.py
package/parse_args.py
package/vcs_p.py
package/work_functions.py
vcs_p_pack-0.1.7.dist-info/METADATA
vcs_p_pack-0.1.7.dist-info/WHEEL
vcs_p_pack-0.1.7.dist-info/entry_points.txt
vcs_p_pack-0.1.7.dist-info/top_level.txt
vcs_p_pack-0.1.7.dist-info/RECORD
