Metadata-Version: 2.1
Name: vcs-p-pack
Version: 0.1.7
Requires-Dist: psutil (==5.9.4)
Requires-Dist: setuptools (==56.0.0)
Requires-Dist: pygit2 (==1.11.1)
Requires-Dist: vcstool (==0.3.0)
